{
  "back": "Back",
  "based": "This score is based on your answers.",
  "FieldScore": "Field Score For Technologies",
  "hint": "Hint",
  "keep": "Keep working on it!",
  "next": "Next",
  "questions": "Questions",
  "ScoreMessage0": "It looks like you're just getting started. Keep practicing!",
  "ScoreMessage1": "You're on the right track, but there's more to learn.",
  "ScoreMessage2": "Good effort! There are some areas for improvement.",
  "ScoreMessage3": "Great job! You have a solid understanding.",
  "ScoreMessage4": "Excellent! You have a strong grasp of the concepts.",
  "showResut": "Show Result",
  "start": "Start",
  "totalScore": "Total Score",
  "welcome": "Welcome The Quiz AI",
  "preparation": "Preparation",
  "formlevel": "Select your level.",
  "selectField": "Which area would you like to be tested on?",
  "informNext": "The technologies to be used will be selected on the next page.",
  "interviewLayout": "Interview preparation form",
  "choosenLevel": "Selected Level:",
  "choosenField": "Selected Field:",
  "yourAnswer": "Your Answer",
  "totalScoreDescription": "This is the overall score for all the questions.",
  "home": "Home",
  "contact": "Contact",
  "features": "Features",
  "subHead": "AI-powered interview simulation for developers.",
  "sectionHeader": "Take the Quiz - Are You Ready to Become a Developer of the Future?",
  "sectionParagrafh": "For those looking to take their software career to the next level, Quiz Al offers a revolutionary AI-powered platform! No matter your role – whether you're a DevOps guru, a Front-end wizard, or a Back-end architect – Quiz Al promises a personalized learning and development experience just for you.",
  "selection": "Some of the fields you can choose from.",
  "error": "You must log in first."
}